mydef/allinone.py
mydef/mydef.py
osstoohardd-0.0.1.dist-info/LICENSE
osstoohardd-0.0.1.dist-info/METADATA
osstoohardd-0.0.1.dist-info/WHEEL
osstoohardd-0.0.1.dist-info/top_level.txt
osstoohardd-0.0.1.dist-info/RECORD
