Metadata-Version: 2.1
Name: osstoohardd
Version: 0.0.1
Summary: quick coding for something
Home-page: https://github.com/ikko030/oss.git
Download-URL: https://github.com/ikko030/oss.git
Author: jieuncheon
Classifier: Programming Language :: Python :: 3
License-File: LICENSE
